collective.faq-3.1.1-py3.13-nspkg.pth
collective/faq/__init__.py
collective/faq/adapters.py
collective/faq/configure.zcml
collective/faq/content.py
collective/faq/interfaces.py
collective/faq/setuphandlers.py
collective/faq/testing.py
collective/faq/upgrades.py
collective/faq/upgrades.zcml
collective/faq/browser/__init__.py
collective/faq/browser/configure.zcml
collective/faq/browser/faq.pt
collective/faq/browser/faq_item.pt
collective/faq/locales/collective.faq.pot
collective/faq/locales/update.sh
collective/faq/locales/de/LC_MESSAGES/collective.faq.mo
collective/faq/locales/de/LC_MESSAGES/collective.faq.po
collective/faq/locales/de/LC_MESSAGES/plone.mo
collective/faq/locales/de/LC_MESSAGES/plone.po
collective/faq/locales/fr/LC_MESSAGES/collective.faq.mo
collective/faq/locales/fr/LC_MESSAGES/collective.faq.po
collective/faq/locales/fr/LC_MESSAGES/plone.mo
collective/faq/locales/fr/LC_MESSAGES/plone.po
collective/faq/locales/it/LC_MESSAGES/collective.faq.mo
collective/faq/locales/it/LC_MESSAGES/collective.faq.po
collective/faq/locales/nl/LC_MESSAGES/collective.faq.mo
collective/faq/locales/nl/LC_MESSAGES/collective.faq.po
collective/faq/profiles/default/browserlayer.xml
collective/faq/profiles/default/diff_tool.xml
collective/faq/profiles/default/metadata.xml
collective/faq/profiles/default/repositorytool.xml
collective/faq/profiles/default/types.xml
collective/faq/profiles/default/registry/displayed_types.xml
collective/faq/profiles/default/registry/icons.xml
collective/faq/profiles/default/types/FAQ.xml
collective/faq/profiles/default/types/FAQ_Item.xml
collective/faq/profiles/uninstall/browserlayer.xml
collective/faq/profiles/uninstall/types.xml
collective/faq/profiles/upgrade_3001/diff_tool.xml
collective/faq/profiles/upgrade_3001/repositorytool.xml
collective/faq/profiles/upgrade_3001/registry/bundles.xml
collective/faq/profiles/upgrade_3001/types/FAQ.xml
collective/faq/profiles/upgrade_3001/types/FAQ_Item.xml
collective_faq-3.1.1.dist-info/METADATA
collective_faq-3.1.1.dist-info/WHEEL
collective_faq-3.1.1.dist-info/entry_points.txt
collective_faq-3.1.1.dist-info/namespace_packages.txt
collective_faq-3.1.1.dist-info/top_level.txt
collective_faq-3.1.1.dist-info/RECORD
