Metadata-Version: 2.4
Name: collective.faq
Version: 3.1.1
Summary: Plone addon package for managing FAQ sections
Home-page: https://github.com/collective/collective.faq
Author: kitconcept GmbH
Author-email: info@kitconcept.com
License: GPL version 2
Keywords: Python Plone
Classifier: Development Status :: 5 - Production/Stable
Classifier: Environment :: Web Environment
Classifier: Framework :: Plone
Classifier: Framework :: Plone :: 6.0
Classifier: Framework :: Plone :: 6.1
Classifier: Framework :: Plone :: 6.2
Classifier: Programming Language :: Python
Classifier: Programming Language :: Python :: 3.9
Classifier: Programming Language :: Python :: 3.10
Classifier: Programming Language :: Python :: 3.11
Classifier: Programming Language :: Python :: 3.12
Classifier: Programming Language :: Python :: 3.13
Classifier: Operating System :: OS Independent
Classifier: License :: OSI Approved :: GNU General Public License v2 (GPLv2)
Requires-Python: >=3.9
Requires-Dist: AccessControl
Requires-Dist: plone.api
Requires-Dist: plone.app.textfield
Requires-Dist: plone.base
Requires-Dist: plone.dexterity
Requires-Dist: plone.supermodel
Requires-Dist: Products.CMFPlone
Requires-Dist: Products.GenericSetup>=1.8.2
Requires-Dist: setuptools
Requires-Dist: zope.configuration>=6.0
Requires-Dist: zope.deprecation
Requires-Dist: zope.i18nmessageid
Requires-Dist: zope.interface
Requires-Dist: zope.publisher
Requires-Dist: zope.schema
Provides-Extra: test
Requires-Dist: plone.app.testing; extra == "test"
Requires-Dist: plone.app.contenttypes[test]; extra == "test"
Requires-Dist: plone.browserlayer; extra == "test"
Requires-Dist: zope.component; extra == "test"
Dynamic: author
Dynamic: author-email
Dynamic: classifier
Dynamic: description
Dynamic: home-page
Dynamic: keywords
Dynamic: license
Dynamic: provides-extra
Dynamic: requires-dist
Dynamic: requires-python
Dynamic: summary
